femagtools/__init__.py
femagtools/airgap.py
femagtools/amazon.py
femagtools/amela.py
femagtools/asm.py
femagtools/bch.py
femagtools/bchxml.py
femagtools/condor.py
femagtools/conductor.py
femagtools/config.py
femagtools/convert.py
femagtools/dakota.py
femagtools/dakota_femag.py
femagtools/dakotaout.py
femagtools/docker.py
femagtools/ecloss.py
femagtools/erg.py
femagtools/femag.py
femagtools/forcedens.py
femagtools/fsl.py
femagtools/getset.py
femagtools/gmsh.py
femagtools/google.py
femagtools/grid.py
femagtools/heat_source_network.py
femagtools/hxy.py
femagtools/isa7.py
femagtools/jhb.py
femagtools/job.py
femagtools/leakinduc.py
femagtools/losscoeffs.py
femagtools/magnet.py
femagtools/mcv.py
femagtools/me.py
femagtools/model.py
femagtools/moproblem.py
femagtools/multiproc.py
femagtools/mxw2msh.py
femagtools/nc.py
femagtools/netlist.py
femagtools/ntib.py
femagtools/opt.py
femagtools/parstudy.py
femagtools/poc.py
femagtools/portpool.py
femagtools/semi_fea.py
femagtools/shortcircuit.py
femagtools/tks.py
femagtools/ts.py
femagtools/utils.py
femagtools/vbf.py
femagtools/vtu.py
femagtools/windings.py
femagtools/zmq.py
femagtools/dxfsl/__init__.py
femagtools/dxfsl/area.py
femagtools/dxfsl/areabuilder.py
femagtools/dxfsl/concat.py
femagtools/dxfsl/conv.py
femagtools/dxfsl/converter.py
femagtools/dxfsl/corner.py
femagtools/dxfsl/dumprenderer.py
femagtools/dxfsl/dxfparser.py
femagtools/dxfsl/femparser.py
femagtools/dxfsl/fslrenderer.py
femagtools/dxfsl/functions.py
femagtools/dxfsl/geom.py
femagtools/dxfsl/journal.py
femagtools/dxfsl/machine.py
femagtools/dxfsl/plotrenderer.py
femagtools/dxfsl/shape.py
femagtools/dxfsl/svgparser.py
femagtools/dxfsl/svgrenderer.py
femagtools/dxfsl/symmetry.py
femagtools/machine/__init__.py
femagtools/machine/afpm.py
femagtools/machine/effloss.py
femagtools/machine/im.py
femagtools/machine/pm.py
femagtools/machine/sizing.py
femagtools/machine/sm.py
femagtools/machine/utils.py
femagtools/moo/__init__.py
femagtools/moo/algorithm.py
femagtools-1.9.1.dist-info/licenses/LICENSE
femagtools-1.9.1.dist-info/METADATA
femagtools-1.9.1.dist-info/WHEEL
femagtools-1.9.1.dist-info/entry_points.txt
femagtools-1.9.1.dist-info/top_level.txt
femagtools-1.9.1.dist-info/RECORD
