Metadata-Version: 2.4
Name: femagtools
Version: 1.9.1
Summary: Python API for FEMAG
Author-email: Ronald Tanner <tar@semafor.ch>, Dapu Zhang <dzhang@gtisoft.com>, Beat Holm <hob@semafor.ch>, Günther Amsler <amg@semafor.ch>, Nicolas Mauchle <mau@semafor.ch>
License: Copyright (c) 2016-2023, Semafor Informatik & Energie AG, Basel
Classifier: Programming Language :: Python :: 3
Classifier: Intended Audience :: Science/Research
Classifier: License :: OSI Approved :: BSD License
Classifier: Topic :: Scientific/Engineering
Requires-Python: >=3.7
License-File: LICENSE
Requires-Dist: numpy
Requires-Dist: scipy
Requires-Dist: mako
Requires-Dist: six
Requires-Dist: lmfit
Requires-Dist: netCDF4>=1.6.5
Provides-Extra: rdp
Requires-Dist: rdp; extra == "rdp"
Provides-Extra: dxfsl
Requires-Dist: ezdxf; extra == "dxfsl"
Requires-Dist: networkx; extra == "dxfsl"
Provides-Extra: svgfsl
Requires-Dist: ezdxf; extra == "svgfsl"
Requires-Dist: networkx; extra == "svgfsl"
Requires-Dist: lxml; extra == "svgfsl"
Provides-Extra: mplot
Requires-Dist: matplotlib; extra == "mplot"
Provides-Extra: meshio
Requires-Dist: meshio; extra == "meshio"
Provides-Extra: vtk
Requires-Dist: vtk; extra == "vtk"
Provides-Extra: zmq
Requires-Dist: pyzmq; extra == "zmq"
Provides-Extra: test
Requires-Dist: pytest; extra == "test"
Provides-Extra: all
Requires-Dist: femagtools[dxfsl,meshio,mplot,svgfsl,test,vtk,zmq]; extra == "all"
Dynamic: license-file
